client/__init__.py
client/clients.py
client/base/__init__.py
client/base/baseDataloader.py
client/base/baseTrainer.py
decentralearn/__init__.py
decentralearn/contracts/__init__.py
decentralearn/contracts/contracts.py
decentralearn/contracts/deploy.py
decentralearn/contracts/fl_contract.py
decentralearn/contracts/model_registry.py
decentralearn/dataset/CIFAR10.py
decentralearn/dataset/CIFAR100.py
decentralearn/dataset/DatasetFactory.py
decentralearn/dataset/DatasetSpliter.py
decentralearn/dataset/EMNIST.py
decentralearn/dataset/FashionMNIST.py
decentralearn/dataset/__init__.py
decentralearn/dataset/test_custom_dataset.py
decentralearn/utils/__init__.py
decentralearn/utils/jsonFormat.py
model/ModelFactory.py
model/SignAlexNet.py
model/VGG.py
model/__init__.py
model/alexnet.py
model/resnet.py
model/simple.py
model/simple_cnn.py
server/__init__.py
server/serverSimulator.py
server/base/__init__.py
server/base/baseAggregator.py
decentralearn-2.1.4.dist-info/LICENSE.md
decentralearn-2.1.4.dist-info/METADATA
decentralearn-2.1.4.dist-info/WHEEL
decentralearn-2.1.4.dist-info/top_level.txt
decentralearn-2.1.4.dist-info/RECORD
